{
  "categories": [
    "String"
  ],
  "diff": "Easy",
  "title": "859. Buddy Strings",
  "question": "<div><p>Given two strings <code>A</code> and <code>B</code>&nbsp;of lowercase letters, return <code>true</code> if and only if we&nbsp;can swap two letters in <code>A</code> so that the result equals <code>B</code>.</p>\n\n<p>&nbsp;</p>\n\n<p><strong>Example 1:</strong></p>\n\n<div>\n<pre><strong>Input: </strong>A = <span id=\"example-input-1-1\">\"ab\"</span>, B = <span id=\"example-input-1-2\">\"ba\"</span>\n<strong>Output: </strong><span id=\"example-output-1\">true</span>\n</pre>\n\n<div>\n<p><strong>Example 2:</strong></p>\n\n<pre><strong>Input: </strong>A = <span id=\"example-input-2-1\">\"ab\"</span>, B = <span id=\"example-input-2-2\">\"ab\"</span>\n<strong>Output: </strong><span id=\"example-output-2\">false</span>\n</pre>\n\n<div>\n<p><strong>Example 3:</strong></p>\n\n<pre><strong>Input: </strong>A = <span id=\"example-input-3-1\">\"aa\"</span>, B = <span id=\"example-input-3-2\">\"aa\"</span>\n<strong>Output: </strong><span id=\"example-output-3\">true</span>\n</pre>\n\n<div>\n<p><strong>Example 4:</strong></p>\n\n<pre><strong>Input: </strong>A = <span id=\"example-input-4-1\">\"aaaaaaabc\"</span>, B = <span id=\"example-input-4-2\">\"aaaaaaacb\"</span>\n<strong>Output: </strong><span id=\"example-output-4\">true</span>\n</pre>\n\n<div>\n<p><strong>Example 5:</strong></p>\n\n<pre><strong>Input: </strong>A = <span id=\"example-input-5-1\">\"\"</span>, B = <span id=\"example-input-5-2\">\"aa\"</span>\n<strong>Output: </strong><span id=\"example-output-5\">false</span>\n</pre>\n\n<p>&nbsp;</p>\n\n<p><strong><span>Note:</span></strong></p>\n\n<ol>\n\t<li><code>0 &lt;= A.length &lt;= 20000</code></li>\n\t<li><code>0 &lt;= B.length &lt;= 20000</code></li>\n\t<li><code>A</code> and&nbsp;<code>B</code> consist only of lowercase letters.</li>\n</ol>\n</div>\n</div>\n</div>\n</div>\n</div>\n</div>",
  "url": "https://leetcode.com/problems/buddy-strings/",
  "companies": {},
  "code": "class Solution(object):\\u000A    def buddyStrings(self, A, B):\\u000A        \\u0022\\u0022\\u0022\\u000A        :type A: str\\u000A        :type B: str\\u000A        :rtype: bool\\u000A        \\u0022\\u0022\\u0022\\u000A        from collections import Counter\\u000A        if len(A) !\\u003D len(B): return False\\u000A        l \\u003D next((i for i in range(len(A)) if A[i] !\\u003D B[i]), None)\\u000A        r \\u003D next((i for i in range(len(A) \\u002D1, \\u002D1, \\u002D1) if A[i] !\\u003D B[i]), None)\\u000A        if l is None: return len(set(A)) !\\u003D len(A)\\u000A        return A[:l] + A[r] + A[l + 1:r] + A[l] + A[r + 1:] \\u003D\\u003D B"
}